gsearch_wrapper/__init__.py
gsearch_wrapper/search.py
gsearch_wrapper-0.3.0.dist-info/licenses/LICENSE
gsearch_wrapper-0.3.0.dist-info/METADATA
gsearch_wrapper-0.3.0.dist-info/WHEEL
gsearch_wrapper-0.3.0.dist-info/top_level.txt
gsearch_wrapper-0.3.0.dist-info/RECORD
