Metadata-Version: 2.4
Name: gsearch-wrapper
Version: 0.3.0
Summary: A pluggable Python wrapper for Google Search (API + Scraping + AI extensions)
Author-email: Amal Alexander <amalalex95@gmail.com>
License: MIT
Project-URL: Homepage, https://github.com/amalalexander/gsearch-wrapper
Project-URL: Bug Tracker, https://github.com/amalalexander/gsearch-wrapper/issues
Requires-Python: >=3.8
License-File: LICENSE
Requires-Dist: requests
Requires-Dist: pandas
Dynamic: license-file
